{"displayFieldName":"","fieldAliases":{"FID":"FID","FID_":"FID_","Id":"Id","X":"X","Y":"Y","Ket":"Ket","F6":"F6"},"geometryType":"esriGeometryPoint","spatialReference":{"wkid":32749,"latestWkid":32749},"fields":[{"name":"FID","type":"esriFieldTypeOID","alias":"FID"},{"name":"FID_","type":"esriFieldTypeString","alias":"FID_","length":254},{"name":"Id","type":"esriFieldTypeDouble","alias":"Id"},{"name":"X","type":"esriFieldTypeDouble","alias":"X"},{"name":"Y","type":"esriFieldTypeDouble","alias":"Y"},{"name":"Ket","type":"esriFieldTypeString","alias":"Ket","length":254},{"name":"F6","type":"esriFieldTypeString","alias":"F6","length":254}],"features":[{"attributes":{"FID":0,"FID_":"Ketua RT 1 RW 20","Id":0.0,"X":438932.88,"Y":9211712.02,"Ket":"Ketua RT","F6":" "},"geometry":{"x":438932.88,"y":9211712.0199999996}},{"attributes":{"FID":1,"FID_":"Ketua RT 2 RW 20","Id":0.0,"X":438963.8,"Y":9211765.8,"Ket":"Ketua RT","F6":" "},"geometry":{"x":438963.79999999999,"y":9211765.8000000007}},{"attributes":{"FID":2,"FID_":"Ketua RT 3 RW 20","Id":0.0,"X":439103.76,"Y":9211947.15,"Ket":"Ketua RT","F6":" "},"geometry":{"x":439103.76000000001,"y":9211947.1500000004}},{"attributes":{"FID":3,"FID_":"Ketua RT 4 RW 20","Id":0.0,"X":439039.11,"Y":9211884.43,"Ket":"Ketua RT","F6":" "},"geometry":{"x":439039.10999999999,"y":9211884.4299999997}},{"attributes":{"FID":4,"FID_":"Ketua RT 5 RW 20","Id":0.0,"X":439014.87,"Y":9211896.99,"Ket":"Ketua RT","F6":" "},"geometry":{"x":439014.87,"y":9211896.9900000002}},{"attributes":{"FID":5,"FID_":"Ketua RW 20","Id":0.0,"X":439033.54,"Y":9211929.26,"Ket":"Ketua RW","F6":" "},"geometry":{"x":439033.53999999998,"y":9211929.2599999998}},{"attributes":{"FID":6,"FID_":"Mushola Al-Ikhlas","Id":0.0,"X":439068.47,"Y":9211958.17,"Ket":"Masjid/Mushola","F6":" "},"geometry":{"x":439068.46999999997,"y":9211958.1699999999}},{"attributes":{"FID":7,"FID_":"Kantor Urusan Agama","Id":0.0,"X":439351.69,"Y":9211362.44,"Ket":"Kantor Urusan Agama","F6":" "},"geometry":{"x":439351.69,"y":9211362.4399999995}},{"attributes":{"FID":8,"FID_":"Masjid Baitul Mutaqin","Id":0.0,"X":439469.04,"Y":9211466.99,"Ket":"Masjid/Mushola","F6":" "},"geometry":{"x":439469.03999999998,"y":9211466.9900000002}},{"attributes":{"FID":9,"FID_":"GKJ Glepung","Id":0.0,"X":439460.96,"Y":9211556.35,"Ket":"Gereja","F6":" "},"geometry":{"x":439460.96000000002,"y":9211556.3499999996}},{"attributes":{"FID":10,"FID_":"SDN 03 Kalongan","Id":0.0,"X":439237.31,"Y":9211589.55,"Ket":"Sekolah","F6":" "},"geometry":{"x":439237.31,"y":9211589.5500000007}},{"attributes":{"FID":11,"FID_":"Posyandu Permata Bunda","Id":0.0,"X":439720.88,"Y":9211714.19,"Ket":"Posyandu","F6":" "},"geometry":{"x":439720.88,"y":9211714.1899999995}},{"attributes":{"FID":12,"FID_":"Kepala Dusun Glepung","Id":0.0,"X":439726.09,"Y":9211720.03,"Ket":"Kepala Dusun","F6":" "},"geometry":{"x":439726.09000000003,"y":9211720.0299999993}},{"attributes":{"FID":13,"FID_":"Masjid Auli'a","Id":0.0,"X":439603.19,"Y":9211638.51,"Ket":"Masjid/Mushola","F6":" "},"geometry":{"x":439603.19,"y":9211638.5099999998}},{"attributes":{"FID":14,"FID_":"Ketua RW 9","Id":0.0,"X":439673.68,"Y":9211689.57,"Ket":"Ketua RW","F6":" "},"geometry":{"x":439673.67999999999,"y":9211689.5700000003}},{"attributes":{"FID":15,"FID_":"Ketua RT 1 RW 9","Id":0.0,"X":439370.08,"Y":9211630.55,"Ket":"Ketua RT","F6":" "},"geometry":{"x":439370.08000000002,"y":9211630.5500000007}},{"attributes":{"FID":16,"FID_":"Ketua RT 2 RW 9","Id":0.0,"X":439914.35,"Y":9211522.49,"Ket":"Ketua RT","F6":" "},"geometry":{"x":439914.34999999998,"y":9211522.4900000002}},{"attributes":{"FID":17,"FID_":"Ketua RT 3 RW 9","Id":0.0,"X":439431.97,"Y":9211691.12,"Ket":"Ketua RT","F6":" "},"geometry":{"x":439431.96999999997,"y":9211691.1199999992}},{"attributes":{"FID":18,"FID_":"Ketua RT 4 RW 9","Id":0.0,"X":439699.45,"Y":9211681.31,"Ket":"Ketua RT","F6":" "},"geometry":{"x":439698.7885403437,"y":9211680.3178105168}},{"attributes":{"FID":19,"FID_":"Ketua RT 5 RW 9","Id":0.0,"X":439646.83,"Y":9211565.16,"Ket":"Ketua RT","F6":" "},"geometry":{"x":439647.88833545003,"y":9211563.0433290992}},{"attributes":{"FID":20,"FID_":"Ketua RT 6 RW 9","Id":0.0,"X":439814.19,"Y":9211666.7,"Ket":"Ketua RT","F6":" "},"geometry":{"x":439814.19,"y":9211666.6999999993}},{"attributes":{"FID":21,"FID_":"Ketua RT 7 RW 9","Id":0.0,"X":439822.43,"Y":9211701.41,"Ket":"Ketua RT","F6":" "},"geometry":{"x":439822.42999999999,"y":9211701.4100000001}},{"attributes":{"FID":22,"FID_":"Ketua RT 8 RW 9","Id":0.0,"X":439618.42,"Y":9211468.09,"Ket":"Ketua RT","F6":" "},"geometry":{"x":439618.41999999998,"y":9211468.0899999999}},{"attributes":{"FID":23,"FID_":"Puskesmas Kalongan","Id":0.0,"X":439112.51,"Y":9211552.25,"Ket":"Puskesmas","F6":" "},"geometry":{"x":439112.51000000001,"y":9211552.25}},{"attributes":{"FID":24,"FID_":"Ketua RT 1 RW 12","Id":0.0,"X":439050.41,"Y":9211668.87,"Ket":"Ketua RT","F6":" "},"geometry":{"x":439050.40999999997,"y":9211668.8699999992}},{"attributes":{"FID":25,"FID_":"Ketua RT 2 RW 12","Id":0.0,"X":439062.77,"Y":9211595.18,"Ket":"Ketua RT","F6":" "},"geometry":{"x":439062.77000000002,"y":9211595.1799999997}},{"attributes":{"FID":26,"FID_":"Ketua RT 3 RW 12","Id":0.0,"X":439001.02,"Y":9211678.02,"Ket":"Ketua RT","F6":" "},"geometry":{"x":439001.02000000002,"y":9211678.0199999996}},{"attributes":{"FID":27,"FID_":"Posyandu","Id":0.0,"X":439007.56,"Y":9211591.73,"Ket":"Posyandu","F6":" "},"geometry":{"x":439007.56,"y":9211591.7300000004}},{"attributes":{"FID":28,"FID_":"Masjid Al-Ikhlas","Id":0.0,"X":439068.64,"Y":9211564.17,"Ket":"Masjid/Mushola","F6":" "},"geometry":{"x":439068.64000000001,"y":9211564.1699999999}},{"attributes":{"FID":29,"FID_":"Ketua RW 18","Id":0.0,"X":439249.37,"Y":9211761.23,"Ket":"Ketua RW","F6":" "},"geometry":{"x":439249.37,"y":9211761.2300000004}},{"attributes":{"FID":30,"FID_":"Ketua RT 1 RW 18","Id":0.0,"X":439093.29,"Y":9211721.12,"Ket":"Ketua RT","F6":" "},"geometry":{"x":439093.28999999998,"y":9211721.1199999992}},{"attributes":{"FID":31,"FID_":"Ketua RT 2 RW 18","Id":0.0,"X":439185.07,"Y":9211665.96,"Ket":"Ketua RT","F6":" "},"geometry":{"x":439185.07000000001,"y":9211665.9600000009}},{"attributes":{"FID":32,"FID_":"Ketua RT 3 RW 18","Id":0.0,"X":439145.37,"Y":9211776.46,"Ket":"Ketua RT","F6":" "},"geometry":{"x":439145.37,"y":9211776.4600000009}},{"attributes":{"FID":33,"FID_":"Ketua RT 4 RW 18","Id":0.0,"X":439699.45,"Y":9211681.31,"Ket":"Ketua RT","F6":" "},"geometry":{"x":439207.85318345838,"y":9211745.9346084204}},{"attributes":{"FID":34,"FID_":"Ketua RT 5 RW 18","Id":0.0,"X":439646.83,"Y":9211565.16,"Ket":"Ketua RT","F6":" "},"geometry":{"x":439308.83734484186,"y":9211826.3307306785}},{"attributes":{"FID":35,"FID_":"Ketua RT 6 RW 18","Id":0.0,"X":439381.49,"Y":9211835.09,"Ket":"Ketua RT","F6":" "},"geometry":{"x":439381.48999999999,"y":9211835.0899999999}},{"attributes":{"FID":36,"FID_":"Posyandu RW 18","Id":0.0,"X":439221.75,"Y":9211779.62,"Ket":"Posyandu","F6":" "},"geometry":{"x":439221.75,"y":9211779.6199999992}},{"attributes":{"FID":37,"FID_":"Masjid Griya Kalongan Indah","Id":0.0,"X":439231.27,"Y":9211767.35,"Ket":"Masjid/Mushola","F6":" "},"geometry":{"x":439231.27000000002,"y":9211767.3499999996}},{"attributes":{"FID":38,"FID_":"Ketua RW 12","Id":0.0,"X":438979.95,"Y":9211598.15,"Ket":"Ketua RW","F6":" "},"geometry":{"x":438979.95000000001,"y":9211598.1500000004}},{"attributes":{"FID":39,"FID_":"Kantor Kecamatan Ungaran Timur","Id":0.0,"X":439087.75,"Y":9211481.59,"Ket":"Kantor Kecamatan","F6":" "},"geometry":{"x":439087.75,"y":9211481.5899999999}},{"attributes":{"FID":40,"FID_":"Alun Alun Kalongan","Id":0.0,"X":439178.54,"Y":9211490.29,"Ket":"Alun Alun","F6":" "},"geometry":{"x":439178.53999999998,"y":9211490.2899999991}},{"attributes":{"FID":41,"FID_":"TK Ananda 2","Id":0.0,"X":439257.33,"Y":9211519.87,"Ket":"Sekolah","F6":" "},"geometry":{"x":439257.33000000002,"y":9211519.8699999992}},{"attributes":{"FID":42,"FID_":"Mushola An-Nur","Id":0.0,"X":439888.24,"Y":9211554.7,"Ket":"Masjid/Mushola","F6":" "},"geometry":{"x":439888.23999999999,"y":9211554.6999999993}},{"attributes":{"FID":43,"FID_":"Mushola Ridhotullah","Id":0.0,"X":439710.84,"Y":9211646.62,"Ket":"Masjid/Mushola","F6":" "},"geometry":{"x":439710.84000000003,"y":9211646.6199999992}}]}